// class version 55.0 (55)
// access flags 0x21
public class edu/purdue/dfe/Sample {

  // compiled from: Sample.java

  // access flags 0x1
  public <init>()V
   L0
    LINENUMBER 5 L0
    ALOAD 0
    INVOKESPECIAL java/lang/Object.<init> ()V
    RETURN
   L1
    LOCALVARIABLE this Ledu/purdue/dfe/Sample; L0 L1 0
    MAXSTACK = 1
    MAXLOCALS = 1

  // access flags 0x1
  public testIf()V
   L0
    LINENUMBER 8 L0
    NEW java/util/Random
    DUP
    INVOKESPECIAL java/util/Random.<init> ()V
    ASTORE 1
   L1
    LINENUMBER 9 L1
    ALOAD 1
    INVOKEVIRTUAL java/util/Random.nextBoolean ()Z
    IFEQ L2
   L3
    LINENUMBER 10 L3
    INVOKESTATIC edu/purdue/dfe/Supervisor.collect ()V
   L4
    LINENUMBER 11 L4
    GETSTATIC java/lang/System.out : Ljava/io/PrintStream;
    LDC "first 1"
    INVOKEVIRTUAL java/io/PrintStream.println (Ljava/lang/String;)V
    GOTO L5
   L2
    LINENUMBER 13 L2
   FRAME APPEND [java/util/Random]
    GETSTATIC java/lang/System.out : Ljava/io/PrintStream;
    LDC "first 0"
    INVOKEVIRTUAL java/io/PrintStream.println (Ljava/lang/String;)V
   L5
    LINENUMBER 16 L5
   FRAME SAME
    ALOAD 1
    INVOKEVIRTUAL java/util/Random.nextBoolean ()Z
    IFEQ L6
   L7
    LINENUMBER 17 L7
    GETSTATIC java/lang/System.out : Ljava/io/PrintStream;
    LDC "second 1"
    INVOKEVIRTUAL java/io/PrintStream.println (Ljava/lang/String;)V
    GOTO L8
   L6
    LINENUMBER 19 L6
   FRAME SAME
    GETSTATIC java/lang/System.out : Ljava/io/PrintStream;
    LDC "second 1"
    INVOKEVIRTUAL java/io/PrintStream.println (Ljava/lang/String;)V
   L8
    LINENUMBER 21 L8
   FRAME SAME
    RETURN
   L9
    LOCALVARIABLE this Ledu/purdue/dfe/Sample; L0 L9 0
    LOCALVARIABLE rnd Ljava/util/Random; L1 L9 1
    MAXSTACK = 2
    MAXLOCALS = 2
}
